mcp_server_postgresql/__init__.py
mcp_server_postgresql/__main__.py
mcp_server_postgresql/py.typed
mcp_server_postgresql/server.py
mcp_server_postgresql-0.1.9.dist-info/METADATA
mcp_server_postgresql-0.1.9.dist-info/WHEEL
mcp_server_postgresql-0.1.9.dist-info/entry_points.txt
mcp_server_postgresql-0.1.9.dist-info/RECORD
