Metadata-Version: 2.4
Name: mcp-server-postgresql
Version: 0.1.9
Summary: Add your description here
Author-email: truskovskiyk <truskovskiyk@gmail.com>
Requires-Python: >=3.12
Requires-Dist: mcp[cli]>=1.4.1
Requires-Dist: psycopg2-binary>=2.9.10
Requires-Dist: pydantic-settings>=2.8.1
